reelname/__init__.py
reelname/__main__.py
reelname/_version.py
reelname/cli.py
reelname/constants.py
reelname/exceptions.py
reelname/reelname.py
reelname/utils.py
reelname-2.0.4.dist-info/METADATA
reelname-2.0.4.dist-info/WHEEL
reelname-2.0.4.dist-info/entry_points.txt
reelname-2.0.4.dist-info/licenses/LICENSE
reelname-2.0.4.dist-info/RECORD
