Metadata-Version: 2.4
Name: reelname
Version: 2.0.4
Summary: A tool to fix media file names
Project-URL: Homepage, https://github.com/viseshrp/reelname
Project-URL: Repository, https://github.com/viseshrp/reelname
Project-URL: Documentation, https://github.com/viseshrp/reelname/blob/main/README.md
Project-URL: Changelog, https://github.com/viseshrp/reelname/blob/main/CHANGELOG.md
Project-URL: Bug-Tracker, https://github.com/viseshrp/reelname/issues
Project-URL: CI, https://github.com/viseshrp/reelname/actions
Author-email: Visesh Prasad <viseshrprasad@gmail.com>
License: MIT
License-File: LICENSE
Keywords: python
Classifier: Development Status :: 4 - Beta
Classifier: Environment :: Console
Classifier: Intended Audience :: Developers
Classifier: License :: OSI Approved :: MIT License
Classifier: Natural Language :: English
Classifier: Operating System :: OS Independent
Classifier: Programming Language :: Python
Classifier: Programming Language :: Python :: 3
Classifier: Programming Language :: Python :: 3.9
Classifier: Programming Language :: Python :: 3.10
Classifier: Programming Language :: Python :: 3.11
Classifier: Programming Language :: Python :: 3.12
Classifier: Programming Language :: Python :: 3.13
Classifier: Topic :: Software Development :: Libraries :: Python Modules
Requires-Python: <4.0,>=3.9
Requires-Dist: aiofiles>=24.1.0
Requires-Dist: cinemagoer>=2023.5.1
Requires-Dist: click>=8.1.1
Requires-Dist: rapidfuzz>=3.13.0
Requires-Dist: watchdog>=6.0.0
